carnitas/__init__.py
carnitas/carnitas.py
carnitas-0.0.1.dist-info/METADATA
carnitas-0.0.1.dist-info/WHEEL
carnitas-0.0.1.dist-info/top_level.txt
carnitas-0.0.1.dist-info/RECORD
